Flask_SQLAlchemy_Database_Orchestration/CHANGELOG.md
Flask_SQLAlchemy_Database_Orchestration/DbCreate.py
Flask_SQLAlchemy_Database_Orchestration/DbInit.py
Flask_SQLAlchemy_Database_Orchestration/DbMigrade.py
Flask_SQLAlchemy_Database_Orchestration/README.md
Flask_SQLAlchemy_Database_Orchestration/Requirements.txt
Flask_SQLAlchemy_Database_Orchestration/Logix/__init__.py
Flask_SQLAlchemy_Database_Orchestration/Logix/DbManager/DbManager.py
Flask_SQLAlchemy_Database_Orchestration/Logix/DbManager/__init__.py
Flask_SQLAlchemy_Database_Orchestration/Logix/DbManager/__pycache__/DbManager.cpython-39.pyc
Flask_SQLAlchemy_Database_Orchestration/Logix/DbManager/__pycache__/__init__.cpython-39.pyc
Flask_SQLAlchemy_Database_Orchestration/Logix/Midware/CreateMigrationMaker.py
Flask_SQLAlchemy_Database_Orchestration/Logix/Midware/HeroKit.py
Flask_SQLAlchemy_Database_Orchestration/Logix/Midware/Multiple.py
Flask_SQLAlchemy_Database_Orchestration/Logix/Midware/RunMigration.py
Flask_SQLAlchemy_Database_Orchestration/Logix/Midware/Single.py
Flask_SQLAlchemy_Database_Orchestration/Logix/Midware/__pycache__/CreateMigrationMaker.cpython-39.pyc
Flask_SQLAlchemy_Database_Orchestration/Logix/Midware/__pycache__/HeroKit.cpython-39.pyc
Flask_SQLAlchemy_Database_Orchestration/Logix/Midware/__pycache__/Multiple.cpython-39.pyc
Flask_SQLAlchemy_Database_Orchestration/Logix/Midware/__pycache__/RunMigration.cpython-39.pyc
Flask_SQLAlchemy_Database_Orchestration/Logix/Midware/__pycache__/Single.cpython-39.pyc
Flask_SQLAlchemy_Database_Orchestration/Logix/Temp/__init__.py
Flask_SQLAlchemy_Database_Orchestration/Logix/Temp/__pycache__/MigrationMaker.cpython-39.pyc
Flask_SQLAlchemy_Database_Orchestration/Logix/Temp/__pycache__/__init__.cpython-39.pyc
Flask_SQLAlchemy_Database_Orchestration/Logix/__pycache__/__init__.cpython-39.pyc
Flask_SQLAlchemy_Database_Orchestration/Models/__init__.py
Flask_SQLAlchemy_Database_Orchestration/Models/BaseModel/BaseModel.py
Flask_SQLAlchemy_Database_Orchestration-1.0.5.dist-info/LICENSE
Flask_SQLAlchemy_Database_Orchestration-1.0.5.dist-info/METADATA
Flask_SQLAlchemy_Database_Orchestration-1.0.5.dist-info/WHEEL
Flask_SQLAlchemy_Database_Orchestration-1.0.5.dist-info/top_level.txt
Flask_SQLAlchemy_Database_Orchestration-1.0.5.dist-info/RECORD
